bsg_api/__init__.py
bsg_api/api_client.py
bsg_api/api_response.py
bsg_api/configuration.py
bsg_api/exceptions.py
bsg_api/py.typed
bsg_api/rest.py
bsg_api/api/__init__.py
bsg_api/api/account_settings_api.py
bsg_api/api/auth_api.py
bsg_api/api/balance_api.py
bsg_api/api/campaign_api.py
bsg_api/api/campaign_rcs_api.py
bsg_api/api/campaign_sms_api.py
bsg_api/api/campaign_whats_app_api.py
bsg_api/api/contact_api.py
bsg_api/api/contact_field_api.py
bsg_api/api/contact_list_api.py
bsg_api/api/email_api.py
bsg_api/api/internal_core_price_api.py
bsg_api/api/internal_country_api.py
bsg_api/api/internal_currency_api.py
bsg_api/api/internal_two_fa_api.py
bsg_api/api/internal_wst_price_api.py
bsg_api/api/messages_sms_api.py
bsg_api/api/messages_whats_app_api.py
bsg_api/api/senders_api.py
bsg_api/api/short_domains_api.py
bsg_api/api/short_links_api.py
bsg_api/api/stop_list_api.py
bsg_api/api/two_fa_templates_api.py
bsg_api/api/two_faotp_api.py
bsg_api/models/__init__.py
bsg_api/models/account_balance200_response.py
bsg_api/models/account_tariffs200_response.py
bsg_api/models/alternative_channel.py
bsg_api/models/balance_schema.py
bsg_api/models/campaign200_response.py
bsg_api/models/campaign_details200_response.py
bsg_api/models/campaign_price200_response.py
bsg_api/models/campaign_price422_response.py
bsg_api/models/campaign_price_request.py
bsg_api/models/campaign_price_request_messages_item.py
bsg_api/models/campaign_schema.py
bsg_api/models/campaign_status.py
bsg_api/models/campaign_stop200_response.py
bsg_api/models/campaign_stop422_response.py
bsg_api/models/cancel_otp200_response.py
bsg_api/models/cancel_otp404_response.py
bsg_api/models/cancel_otp422_response.py
bsg_api/models/card.py
bsg_api/models/cards.py
bsg_api/models/click_resource.py
bsg_api/models/components.py
bsg_api/models/contact200_response.py
bsg_api/models/contact422_response.py
bsg_api/models/contact_create201_response.py
bsg_api/models/contact_create422_response.py
bsg_sdk-0.1.0.dist-info/METADATA
bsg_sdk-0.1.0.dist-info/WHEEL
bsg_sdk-0.1.0.dist-info/top_level.txt
bsg_sdk-0.1.0.dist-info/RECORD
