Metadata-Version: 2.4
Name: bsg-sdk
Version: 0.1.0
Summary: BSG Python SDK for One-API
Home-page: https://github.com/bsgworld/python-sdk
Author: BSG World
Author-email: BSG World <support@bsg.world>
Maintainer-email: BSG World <support@bsg.world>
License: MIT
Project-URL: Homepage, https://bsg.world
Project-URL: Documentation, https://bsg.world/developers
Project-URL: Repository, https://github.com/bsgworld/python-sdk
Project-URL: Issues, https://github.com/bsgworld/python-sdk/issues
Keywords: BSG,SMS,Viber,WhatsApp,RCS,API,SDK
Classifier: Development Status :: 4 - Beta
Classifier: Intended Audience :: Developers
Classifier: License :: OSI Approved :: MIT License
Classifier: Operating System :: OS Independent
Classifier: Programming Language :: Python :: 3
Classifier: Programming Language :: Python :: 3.8
Classifier: Programming Language :: Python :: 3.9
Classifier: Programming Language :: Python :: 3.10
Classifier: Programming Language :: Python :: 3.11
Classifier: Programming Language :: Python :: 3.12
Classifier: Topic :: Communications
Classifier: Topic :: Software Development :: Libraries :: Python Modules
Requires-Python: >= 3.8
Requires-Dist: urllib3<3.0.0,>=1.25.3
Requires-Dist: python-dateutil>=2.8.2
Requires-Dist: pydantic>=2
Requires-Dist: typing-extensions>=4.7.1
Provides-Extra: dev
Requires-Dist: pytest>=7.2.1; extra == "dev"
Requires-Dist: pytest-cov>=2.8.1; extra == "dev"
Requires-Dist: tox>=3.9.0; extra == "dev"
Requires-Dist: flake8>=4.0.0; extra == "dev"
Requires-Dist: types-python-dateutil>=2.8.19.14; extra == "dev"
Requires-Dist: mypy>=1.5; extra == "dev"
Dynamic: author
Dynamic: home-page
Dynamic: requires-python
